{
 "chart_name": "Tracker Company Wise Vehicles",
 "chart_type": "Group By",
 "creation": "2025-08-15 11:13:00.069628",
 "docstatus": 0,
 "doctype": "Dashboard Chart",
 "document_type": "Vehicle",
 "dynamic_filters_json": "[]",
 "filters_json": "[]",
 "group_by_based_on": "tracker",
 "group_by_type": "Count",
 "idx": 0,
 "is_public": 1,
 "is_standard": 1,
 "last_synced_on": "2025-08-15 11:02:17.946000",
 "modified": "2025-08-15 11:15:47.994198",
 "modified_by": "Administrator",
 "module": "Fleet System",
 "name": "Tracker Company Wise Vehicles",
 "number_of_groups": 0,
 "owner": "Administrator",
 "roles": [],
 "time_interval": "Yearly",
 "timeseries": 0,
 "timespan": "Last Year",
 "type": "Pie",
 "use_report_chart": 0,
 "y_axis": []
}